Workbook

Sheet Feature Matrix
A1: POWER PLATFORM FEATURE PRIORITIZATION MATRIX
A2: Edit blue 1–10 score cells and the Scoring Weights sheet. Rankings, tiers, and RICE recalculate automatically in Excel.
A4: ID | B4: Category | C4: Feature | D4: Target Phase | E4: Market Demand | F4: Revenue Potential | G4: SEO Value | H4: Differentiation | I4: Effort Efficiency | J4: Weighted Score | K4: Rank | L4: Priority Tier | M4: Confidence | N4: Reach | O4: Impact | P4: Effort | Q4: RICE Score | R4: Recommended Model | S4: Strategic Rationale | T4: Owner | U4: Status | V4: Notes
A5: 1 | B5: Power Apps | C5: Power Apps Component Library | D5: MVP | E5: 10 | F5: 9 | G5: 9 | H5: 9 | I5: 8 | J5: =ROUND(SUMPRODUCT(E5:I5,'Scoring Weights'!$B$4:$B$8)*10,1) | K5: =RANK.EQ(J5,$J$5:$J$64,0) | L5: =IF(J5>='Scoring Weights'!$B$13,'Scoring Weights'!$A$13,IF(J5>='Scoring Weights'!$B$14,'Scoring Weights'!$A$14,IF(J5>='Scoring Weights'!$B$15,'Scoring Weights'!$A$15,'Scoring Weights'!$A$16))) | M5: 9 | N5: 10 | O5: 10 | P5: 3 | Q5: =ROUND((N5*O5*M5)/P5,1) | R5: Freemium + Pro | S5: Core acquisition wedge; reusable production UI assets | U5: Backlog
A6: 2 | B6: Power Apps | C6: Power Apps YAML Exporter | D6: MVP | E6: 10 | F6: 9 | G6: 8 | H6: 10 | I6: 7 | J6: =ROUND(SUMPRODUCT(E6:I6,'Scoring Weights'!$B$4:$B$8)*10,1) | K6: =RANK.EQ(J6,$J$5:$J$64,0) | L6: =IF(J6>='Scoring Weights'!$B$13,'Scoring Weights'!$A$13,IF(J6>='Scoring Weights'!$B$14,'Scoring Weights'!$A$14,IF(J6>='Scoring Weights'!$B$15,'Scoring Weights'!$A$15,'Scoring Weights'!$A$16))) | M6: 8 | N6: 9 | O6: 10 | P6: 4 | Q6: =ROUND((N6*O6*M6)/P6,1) | R6: Pro subscription | S6: Converts discovery into immediate maker productivity | U6: Backlog
A7: 3 | B7: Power Apps | C7: Responsive Layout Library | D7: MVP | E7: 10 | F7: 8 | G7: 9 | H7: 8 | I7: 9 | J7: =ROUND(SUMPRODUCT(E7:I7,'Scoring Weights'!$B$4:$B$8)*10,1) | K7: =RANK.EQ(J7,$J$5:$J$64,0) | L7: =IF(J7>='Scoring Weights'!$B$13,'Scoring Weights'!$A$13,IF(J7>='Scoring Weights'!$B$14,'Scoring Weights'!$A$14,IF(J7>='Scoring Weights'!$B$15,'Scoring Weights'!$A$15,'Scoring Weights'!$A$16))) | M7: 9 | N7: 10 | O7: 9 | P7: 2 | Q7: =ROUND((N7*O7*M7)/P7,1) | R7: Freemium | S7: Common implementation pain with fast time to value | U7: Backlog
A8: 4 | B8: Power Apps | C8: Enterprise Design System | D8: Growth | E8: 9 | F8: 10 | G8: 7 | H8: 10 | I8: 5 | J8: =ROUND(SUMPRODUCT(E8:I8,'Scoring Weights'!$B$4:$B$8)*10,1) | K8: =RANK.EQ(J8,$J$5:$J$64,0) | L8: =IF(J8>='Scoring Weights'!$B$13,'Scoring Weights'!$A$13,IF(J8>='Scoring Weights'!$B$14,'Scoring Weights'!$A$14,IF(J8>='Scoring Weights'!$B$15,'Scoring Weights'!$A$15,'Scoring Weights'!$A$16))) | M8: 8 | N8: 8 | O8: 10 | P8: 7 | Q8: =ROUND((N8*O8*M8)/P8,1) | R8: Enterprise license | S8: High-value standardization for consulting and enterprises | U8: Backlog
A9: 5 | B9: Power Apps | C9: Government UX Toolkit | D9: Growth | E9: 8 | F9: 10 | G9: 6 | H9: 10 | I9: 6 | J9: =ROUND(SUMPRODUCT(E9:I9,'Scoring Weights'!$B$4:$B$8)*10,1) | K9: =RANK.EQ(J9,$J$5:$J$64,0) | L9: =IF(J9>='Scoring Weights'!$B$13,'Scoring Weights'!$A$13,IF(J9>='Scoring Weights'!$B$14,'Scoring Weights'!$A$14,IF(J9>='Scoring Weights'!$B$15,'Scoring Weights'!$A$15,'Scoring Weights'!$A$16))) | M9: 8 | N9: 6 | O9: 10 | P9: 6 | Q9: =ROUND((N9*O9*M9)/P9,1) | R9: Pack + enterprise | S9: Defensible public-sector accessibility niche | U9: Backlog
A10: 6 | B10: Power Apps | C10: Accessibility Template Pack | D10: MVP | E10: 9 | F10: 9 | G10: 8 | H10: 9 | I10: 8 | J10: =ROUND(SUMPRODUCT(E10:I10,'Scoring Weights'!$B$4:$B$8)*10,1) | K10: =RANK.EQ(J10,$J$5:$J$64,0) | L10: =IF(J10>='Scoring Weights'!$B$13,'Scoring Weights'!$A$13,IF(J10>='Scoring Weights'!$B$14,'Scoring Weights'!$A$14,IF(J10>='Scoring Weights'!$B$15,'Scoring Weights'!$A$15,'Scoring Weights'!$A$16))) | M10: 9 | N10: 8 | O10: 9 | P10: 3 | Q10: =ROUND((N10*O10*M10)/P10,1) | R10: Premium pack | S10: Practical compliance accelerator | U10: Backlog
A11: 7 | B11: Power Apps | C11: Canvas App Template Marketplace | D11: MVP | E11: 9 | F11: 9 | G11: 9 | H11: 8 | I11: 7 | J11: =ROUND(SUMPRODUCT(E11:I11,'Scoring Weights'!$B$4:$B$8)*10,1) | K11: =RANK.EQ(J11,$J$5:$J$64,0) | L11: =IF(J11>='Scoring Weights'!$B$13,'Scoring Weights'!$A$13,IF(J11>='Scoring Weights'!$B$14,'Scoring Weights'!$A$14,IF(J11>='Scoring Weights'!$B$15,'Scoring Weights'!$A$15,'Scoring Weights'!$A$16))) | M11: 8 | N11: 9 | O11: 9 | P11: 5 | Q11: =ROUND((N11*O11*M11)/P11,1) | R11: Marketplace commission | S11: Broad marketplace entry point | U11: Backlog
A12: 8 | B12: Power Apps | C12: Form Template Library | D12: MVP | E12: 9 | F12: 8 | G12: 9 | H12: 7 | I12: 9 | J12: =ROUND(SUMPRODUCT(E12:I12,'Scoring Weights'!$B$4:$B$8)*10,1) | K12: =RANK.EQ(J12,$J$5:$J$64,0) | L12: =IF(J12>='Scoring Weights'!$B$13,'Scoring Weights'!$A$13,IF(J12>='Scoring Weights'!$B$14,'Scoring Weights'!$A$14,IF(J12>='Scoring Weights'!$B$15,'Scoring Weights'!$A$15,'Scoring Weights'!$A$16))) | M12: 9 | N12: 9 | O12: 8 | P12: 2 | Q12: =ROUND((N12*O12*M12)/P12,1) | R12: Freemium | S12: High-frequency maker need | U12: Backlog
A13: 9 | B13: Power Apps | C13: Dashboard Screen Templates | D13: MVP | E13: 9 | F13: 8 | G13: 8 | H13: 8 | I13: 9 | J13: =ROUND(SUMPRODUCT(E13:I13,'Scoring Weights'!$B$4:$B$8)*10,1) | K13: =RANK.EQ(J13,$J$5:$J$64,0) | L13: =IF(J13>='Scoring Weights'!$B$13,'Scoring Weights'!$A$13,IF(J13>='Scoring Weights'!$B$14,'Scoring Weights'!$A$14,IF(J13>='Scoring Weights'!$B$15,'Scoring Weights'!$A$15,'Scoring Weights'!$A$16))) | M13: 9 | N13: 8 | O13: 8 | P13: 2 | Q13: =ROUND((N13*O13*M13)/P13,1) | R13: Premium pack | S13: Visual acquisition and bundle potential | U13: Backlog
A14: 10 | B14: Power Apps | C14: PCF Control Marketplace | D14: Scale | E14: 9 | F14: 10 | G14: 8 | H14: 8 | I14: 4 | J14: =ROUND(SUMPRODUCT(E14:I14,'Scoring Weights'!$B$4:$B$8)*10,1) | K14: =RANK.EQ(J14,$J$5:$J$64,0) | L14: =IF(J14>='Scoring Weights'!$B$13,'Scoring Weights'!$A$13,IF(J14>='Scoring Weights'!$B$14,'Scoring Weights'!$A$14,IF(J14>='Scoring Weights'!$B$15,'Scoring Weights'!$A$15,'Scoring Weights'!$A$16))) | M14: 7 | N14: 8 | O14: 10 | P14: 9 | Q14: =ROUND((N14*O14*M14)/P14,1) | R14: Marketplace commission | S14: Higher technical value but support-heavy | U14: Backlog
A15: 11 | B15: Power Apps | C15: Theme and Palette Generator | D15: MVP | E15: 10 | F15: 8 | G15: 10 | H15: 8 | I15: 9 | J15: =ROUND(SUMPRODUCT(E15:I15,'Scoring Weights'!$B$4:$B$8)*10,1) | K15: =RANK.EQ(J15,$J$5:$J$64,0) | L15: =IF(J15>='Scoring Weights'!$B$13,'Scoring Weights'!$A$13,IF(J15>='Scoring Weights'!$B$14,'Scoring Weights'!$A$14,IF(J15>='Scoring Weights'!$B$15,'Scoring Weights'!$A$15,'Scoring Weights'!$A$16))) | M15: 9 | N15: 10 | O15: 8 | P15: 2 | Q15: =ROUND((N15*O15*M15)/P15,1) | R15: Freemium + sponsorship | S15: SEO-friendly free tool and lead magnet | U15: Backlog
A16: 12 | B16: Power Apps | C16: Component AI Configurator | D16: Growth | E16: 9 | F16: 9 | G16: 8 | H16: 10 | I16: 5 | J16: =ROUND(SUMPRODUCT(E16:I16,'Scoring Weights'!$B$4:$B$8)*10,1) | K16: =RANK.EQ(J16,$J$5:$J$64,0) | L16: =IF(J16>='Scoring Weights'!$B$13,'Scoring Weights'!$A$13,IF(J16>='Scoring Weights'!$B$14,'Scoring Weights'!$A$14,IF(J16>='Scoring Weights'!$B$15,'Scoring Weights'!$A$15,'Scoring Weights'!$A$16))) | M16: 7 | N16: 8 | O16: 9 | P16: 8 | Q16: =ROUND((N16*O16*M16)/P16,1) | R16: Pro subscription | S16: Strong differentiation with export upsell | U16: Backlog
... A64: 60 | B64: Marketplace | C64: Creator Marketplace Platform | D64: Scale | E64: 9 | F64: 10 | G64: 9 | H64: 10 | I64: 3 | J64: =ROUND(SUMPRODUCT(E64:I64,'Scoring Weights'!$B$4:$B$8)*10,1) | K64: =RANK.EQ(J64,$J$5:$J$64,0) | L64: =IF(J64>='Scoring Weights'!$B$13,'Scoring Weights'!$A$13,IF(J64>='Scoring Weights'!$B$14,'Scoring Weights'!$A$14,IF(J64>='Scoring Weights'!$B$15,'Scoring Weights'!$A$15,'Scoring Weights'!$A$16))) | M64: 7 | N64: 9 | O64: 10 | P64: 10 | Q64: =ROUND((N64*O64*M64)/P64,1) | R64: Commission + subscription | S64: Long-term network-effect moat | U64: Backlog

Sheet Scoring Weights
A1: WEIGHTED SCORING MODEL
A3: Criterion | B3: Weight | C3: Scoring guidance | D3: Direction
A4: Market Demand | B4: 0.3 | C4: 1 = niche/uncertain; 10 = broad, recurring pain | D4: Higher is better
A5: Revenue Potential | B5: 0.25 | C5: 1 = weak willingness to pay; 10 = strong recurring/enterprise value | D5: Higher is better
A6: SEO Value | B6: 0.15 | C6: 1 = little search intent; 10 = broad evergreen search demand | D6: Higher is better
A7: Competitive Differentiation | B7: 0.2 | C7: 1 = commodity; 10 = clear defensible advantage | D7: Higher is better
A8: Effort Efficiency | B8: 0.1 | C8: 1 = very costly/slow; 10 = fast and inexpensive | D8: Higher is better
A10: Total | B10: =SUM(B4:B8)
A12: Decision thresholds
A13: Tier 1: Build Now | B13: 85
A14: Tier 2: Next | B14: 78
A15: Tier 3: Later | B15: 70
A16: Tier 4: Explore | B16: 0
A19: How the score works
A20: Weighted Score = SUM(each 1-10 score × its weight) × 10. Change blue cells to run scenarios.

Sheet Roadmap View
A1: ROADMAP & PORTFOLIO VIEW
A3: Headline metrics
A5: Total features | C5: Tier 1 candidates | E5: MVP candidates | G5: Average weighted score
A6: =COUNTA('Feature Matrix'!C5:C64) | C6: =COUNTIF('Feature Matrix'!L5:L64,"Tier 1*") | E6: =COUNTIF('Feature Matrix'!D5:D64,"MVP") | G6: =ROUND(AVERAGE('Feature Matrix'!J5:J64),1)
A9: Phase summary | F9: Category portfolio
A10: Phase | B10: Feature Count | C10: Average Score | D10: Suggested focus | F10: Category | G10: Count | H10: Average Score
A11: MVP | B11: =COUNTIF('Feature Matrix'!D$5:D$64,A11) | C11: =ROUND(AVERAGEIF('Feature Matrix'!D$5:D$64,A11,'Feature Matrix'!J$5:J$64),1) | D11: Acquisition wedge and first revenue | F11: AI | G11: =COUNTIF('Feature Matrix'!B$5:B$64,F11) | H11: =ROUND(AVERAGEIF('Feature Matrix'!B$5:B$64,F11,'Feature Matrix'!J$5:J$64),1)
A12: Growth | B12: =COUNTIF('Feature Matrix'!D$5:D$64,A12) | C12: =ROUND(AVERAGEIF('Feature Matrix'!D$5:D$64,A12,'Feature Matrix'!J$5:J$64),1) | D12: Enterprise depth and retention | F12: Architecture | G12: =COUNTIF('Feature Matrix'!B$5:B$64,F12) | H12: =ROUND(AVERAGEIF('Feature Matrix'!B$5:B$64,F12,'Feature Matrix'!J$5:J$64),1)
A13: Scale | B13: =COUNTIF('Feature Matrix'!D$5:D$64,A13) | C13: =ROUND(AVERAGEIF('Feature Matrix'!D$5:D$64,A13,'Feature Matrix'!J$5:J$64),1) | D13: Defensible SaaS and network effects | F13: Community | G13: =COUNTIF('Feature Matrix'!B$5:B$64,F13) | H13: =ROUND(AVERAGEIF('Feature Matrix'!B$5:B$64,F13,'Feature Matrix'!J$5:J$64),1)
F14: Developer Tools | G14: =COUNTIF('Feature Matrix'!B$5:B$64,F14) | H14: =ROUND(AVERAGEIF('Feature Matrix'!B$5:B$64,F14,'Feature Matrix'!J$5:J$64),1)
F15: Governance | G15: =COUNTIF('Feature Matrix'!B$5:B$64,F15) | H15: =ROUND(AVERAGEIF('Feature Matrix'!B$5:B$64,F15,'Feature Matrix'!J$5:J$64),1)
F16: Marketplace | G16: =COUNTIF('Feature Matrix'!B$5:B$64,F16) | H16: =ROUND(AVERAGEIF('Feature Matrix'!B$5:B$64,F16,'Feature Matrix'!J$5:J$64),1)
F17: Power Apps | G17: =COUNTIF('Feature Matrix'!B$5:B$64,F17) | H17: =ROUND(AVERAGEIF('Feature Matrix'!B$5:B$64,F17,'Feature Matrix'!J$5:J$64),1)
F18: Power Automate | G18: =COUNTIF('Feature Matrix'!B$5:B$64,F18) | H18: =ROUND(AVERAGEIF('Feature Matrix'!B$5:B$64,F18,'Feature Matrix'!J$5:J$64),1)
F19: Power BI | G19: =COUNTIF('Feature Matrix'!B$5:B$64,F19) | H19: =ROUND(AVERAGEIF('Feature Matrix'!B$5:B$64,F19,'Feature Matrix'!J$5:J$64),1)

Sheet Instructions
A1: HOW TO USE THIS WORKBOOK
A3: 1. Adjust weights | B3: On Scoring Weights, edit the blue percentages. Keep the total at 100%.
A4: 2. Score features | B4: On Feature Matrix, edit blue 1–10 input cells. Effort Efficiency is inverse, so 10 means fast/easy.
A5: 3. Compare outputs | B5: Weighted Score, Rank, Priority Tier, and RICE Score update automatically.
A6: 4. Plan delivery | B6: Use Target Phase, Owner, Status, and Notes to convert prioritization into an active backlog.
A7: 5. Filter decisions | B7: Filter by Category, Tier, Phase, business model, owner, or status.
A8: 6. Revisit monthly | B8: Update confidence and input scores as customer interviews, analytics, and sales evidence accumulate.
A11: Scoring interpretation
A12: 9–10 | B12: Exceptional / clear evidence
A13: 7–8 | B13: Strong
A14: 5–6 | B14: Moderate / validate
A15: 3–4 | B15: Weak
A16: 1–2 | B16: Very weak / speculative
A19: Important note | B19: Initial scores are strategic assumptions from the feature matrix. Replace them with evidence from interviews, search demand, conversion tests, and sales discovery.
